stdconfigparser.py
StdConfigParser-1.0.1.dist-info/LICENSE
StdConfigParser-1.0.1.dist-info/WHEEL
StdConfigParser-1.0.1.dist-info/METADATA
StdConfigParser-1.0.1.dist-info/RECORD
