Metadata-Version: 1.2
Name: StdConfigParser
Version: 1.0.1
Summary: A standard INI style configuration parser.
Home-page: https://github.com/tds333/stdconfigparser
License: MIT
Keywords: configuration config ini parser configparser configuration
Author: Wolfgang Langner
Author-email: tds333@mailbox.org
Requires-Python: >= 2.7
Classifier: License :: OSI Approved :: MIT License
Classifier: Development Status :: 5 - Production/Stable
Classifier: Intended Audience :: Developers
Classifier: Topic :: Text Processing
Classifier: Topic :: Software Development :: Libraries
Classifier: Programming Language :: Python :: 2
Classifier: Programming Language :: Python :: 3
Classifier: Programming Language :: Python :: 2.7
Classifier: Programming Language :: Python :: 3.3
Classifier: Programming Language :: Python :: 3.4
Classifier: Programming Language :: Python :: 3.5
Classifier: Programming Language :: Python :: 3.6
